{
    "name": "Dialog",
    "description": "A prompt that allows the user to make an important decision. Read more [here](https://m3.material.io/components/dialogs/overview).",
    "functions": [
        {
            "names": [
                "new"
            ],
            "key": "",
            "parameters": [
                {
                    "name": "buttons",
                    "type": "{ ButtonData }",
                    "default": "{}"
                },
                {
                    "name": "icon",
                    "type": "ImageData?",
                    "default": "nil"
                },
                {
                    "name": "headline",
                    "type": "string?",
                    "default": "nil"
                },
                {
                    "name": "description",
                    "type": "string?",
                    "default": "nil"
                },
                {
                    "name": "surfaceColor",
                    "type": "Color3",
                    "default": "Color3.new()"
                },
                {
                    "name": "buttonTextColor",
                    "type": "Color3",
                    "default": "Color3.new()"
                },
                {
                    "name": "disabledTextColor",
                    "type": "Color3",
                    "default": "Color3.new()"
                },
                {
                    "name": "headlineColor",
                    "type": "Color3",
                    "default": "Color3.new()"
                },
                {
                    "name": "descriptionColor",
                    "type": "Color3",
                    "default": "Color3.new()"
                },
                {
                    "name": "scrimColor",
                    "type": "Color3",
                    "default": "Color3.new()"
                },
                {
                    "name": "schemeType",
                    "type": "Enums.SchemeType",
                    "default": "Enums.SchemeType.Light"
                },
                {
                    "name": "headlineFontData",
                    "type": "FontData",
                    "default": "Types.FontData.new(Font.fromEnum(Enum.Font.SourceSans), 14)"
                },
                {
                    "name": "bodyFontData",
                    "type": "FontData",
                    "default": "Types.FontData.new(Font.fromEnum(Enum.Font.SourceSans), 14)"
                },
                {
                    "name": "buttonFontData",
                    "type": "FontData",
                    "default": "Types.FontData.new(Font.fromEnum(Enum.Font.SourceSans), 14)"
                },
                {
                    "name": "scale",
                    "type": "number",
                    "default": "1"
                }
            ]
        },
        {
            "names": [
                "primary",
                "secondary",
                "tertiary"
            ],
            "key": "styled",
            "parameters": [
                {
                    "name": "style",
                    "type": "Style",
                    "default": "Style.new(1, Enum.Font.SourceSans, \"Light\", Color3.new(0, 0.4, 0.7))"
                },
                {
                    "name": "buttons",
                    "type": "{ ButtonData }",
                    "default": "{}"
                },
                {
                    "name": "icon",
                    "type": "ImageData?",
                    "default": "nil"
                },
                {
                    "name": "headline",
                    "type": "string?",
                    "default": "nil"
                },
                {
                    "name": "description",
                    "type": "string?",
                    "default": "nil"
                }
            ]
        }
    ]
}